Ncore/__init__.py
Ncore/client.py
Ncore/rsa.py
Ncore/session.py
Ncore/tl.cpython-313-x86_64-linux-gnu.so
Ncore/tl_object.py
Ncore/tl_schema.json
Ncore/utils.py
Ncore/methods/__init__.py
Ncore/methods/send_message.py
Ncore/types/__init__.py
Ncore/types/input_peer.py
ncore-0.9.64.dist-info/METADATA
ncore-0.9.64.dist-info/WHEEL
ncore-0.9.64.dist-info/top_level.txt
ncore-0.9.64.dist-info/RECORD
ncore-0.9.64.dist-info/licenses/LICENSE
