Metadata-Version: 2.4
Name: Ncore
Version: 0.9.64
Summary: Высокопроизводительная асинхронная библиотека для работы с MTProto (Telegram API).
Author: zovdev
License: Apache-2.0
Project-URL: Homepage, https://github.com/zovdev/Ncore
Project-URL: Bug Tracker, https://github.com/zovdev/Ncore/issues
Keywords: telegram,asyncio,mtproto,telegram-api,telegram-bot
Classifier: Development Status :: 4 - Beta
Classifier: License :: OSI Approved :: Apache Software License
Classifier: Programming Language :: Python :: 3
Classifier: Programming Language :: Python :: 3.10
Classifier: Programming Language :: Python :: 3.11
Classifier: Programming Language :: Python :: 3.12
Classifier: Programming Language :: Python :: 3.13
Classifier: Programming Language :: Python :: 3.14
Classifier: Operating System :: OS Independent
Classifier: Topic :: Software Development :: Libraries :: Python Modules
Requires-Python: <3.15,>=3.10
License-File: LICENSE
Requires-Dist: msgpack>=1.1.0
Requires-Dist: tgcrypto>=1.2.5
Dynamic: license-file
